{"doc_id":"1.pdf","version":"3.4-segment-only","meta":{"profile":"Esi Invoice Extractor V1","fail_mode":"hard"},"header":{"buyer_name":{"raw_text":"To :Seax Malaysia","value_text":"Seax Malaysia","page":1,"source_region":"buyer_name","region_bbox":[0.055556,0.194528,0.292902,0.216523],"token_span":[41,42,43],"confidence":0.9,"strategy":"first_line_pattern","value":"Seax Malaysia","meta":{"strategy":"first_line_pattern","confidence_bucket":"high","line_index":0,"line_bbox":[0.05555555555555555,0.19452840909090913,0.29290196078431374,0.2065233585858586],"line_text_len":17,"raw_line":"To :Seax Malaysia","pattern_used":":\\s*(.+)","pattern_index":0,"group_used":1,"match_span":[3,17],"total_patterns":1}},"invoice_number":{"raw_text":"Invoice No. :INV/076/0825 Payment Term(s) :100% upront before","value_text":"INV/076/0825","page":1,"source_region":"invoice_number","region_bbox":[0.055556,0.252432,0.284183,0.272432],"token_span":[63,64,65,66,67,68,69,70],"confidence":"high","strategy":"regex_capture","regex":{"total_patterns":1,"pattern_index":0,"matched_pattern":"Invoice\\s+No\\.\\s*:\\s*([A-Z0-9\\/]+)","match_span":[0,25]}},"invoice_date":{"raw_text":"Invoice Date :29 August 2025 Invoice No. :INV/076/0825","value_text":"29 August 2025","page":1,"source_region":"invoice_date","region_bbox":[0.055556,0.240058,0.295817,0.260058],"token_span":[58,59,60,61,62,63,64,65],"confidence":"high","strategy":"regex_capture","regex":{"total_patterns":1,"pattern_index":0,"matched_pattern":"Invoice\\s+Date\\s*:\\s*(\\d{1,2}\\s+[A-Za-z]+\\s+\\d{4})","match_span":[0,28]}},"seller_name":{"raw_text":null,"value_text":"PT Electronic Science Indonesia","page":null,"source_region":"override","region_bbox":null,"token_span":[],"confidence":"none","strategy":"constant"}},"totals_extracted":{"subtotal":{"raw_text":"Sub total Rp 39.146.622,00","value_text":"39.146.622,00","page":1,"source_region":"subtotal","region_bbox":[0.718954,0.723665,0.953668,0.743665],"token_span":[175,176,177,178],"confidence":"high","strategy":"regex_capture","regex":{"total_patterns":1,"pattern_index":0,"matched_pattern":"Rp\\s+([\\d,\\.]+)","match_span":[10,26]}},"tax_base":{"raw_text":"Sub total Rp 39.146.622,00 Tax Based VAT Rp 35,884,404.00 VAT Rp 4.306.128,00 Grand Total Rp 43.452.750,00","value_text":"35,884,404.00","page":1,"source_region":"total","region_bbox":[0.706209,0.716089,0.953668,0.801316],"token_span":[175,176,177,178,179,180,181,182,183,185,186,187,196,197,198,199],"confidence":"medium","strategy":"regex_capture","regex":{"total_patterns":1,"pattern_index":0,"matched_pattern":"Based\\s+VAT\\s+Rp\\s+([\\d,\\.]+)","match_span":[31,57]}},"tax":{"raw_text":null,"value_text":"11%","page":null,"source_region":"override","region_bbox":null,"token_span":[],"confidence":"none","strategy":"constant"},"tax_amount":{"raw_text":"VAT Rp 4.306.128,00","value_text":"4.306.128,00","page":1,"source_region":"vat","region_bbox":[0.718954,0.76715,0.953668,0.78715],"token_span":[185,186,187],"confidence":"high","strategy":"regex_capture","regex":{"total_patterns":1,"pattern_index":0,"matched_pattern":"VAT\\s+Rp\\s+([\\d,\\.]+)","match_span":[0,19]}},"income_tax":{"raw_text":null,"value_text":"","page":null,"source_region":"override","region_bbox":null,"token_span":[],"confidence":"none","strategy":"constant"},"income_tax_amount":{"raw_text":null,"value_text":"","page":null,"source_region":"override","region_bbox":null,"token_span":[],"confidence":"none","strategy":"constant"},"grand_total":{"raw_text":"Sub total Rp 39.146.622,00 Tax Based VAT Rp 35,884,404.00 VAT Rp 4.306.128,00 Grand Total Rp 43.452.750,00","value_text":"39.146.622,00","page":1,"source_region":"total","region_bbox":[0.706209,0.716089,0.953668,0.801316],"token_span":[175,176,177,178,179,180,181,182,183,185,186,187,196,197,198,199],"confidence":"medium","strategy":"regex_capture","regex":{"total_patterns":1,"pattern_index":0,"matched_pattern":"total\\s+Rp\\s+([\\d,\\.]+)","match_span":[4,26]}}}}