{
  "1": [
    {
      "name": "COL1",
      "x0": 0.0,
      "x1": 0.08669354838709677
    },
    {
      "name": "NO",
      "x0": 0.08669354838709677,
      "x1": 0.13629032258064516
    },
    {
      "name": "DESC",
      "x0": 0.13629032258064516,
      "x1": 0.5338709677419355
    },
    {
      "name": "UNIT_PRICE",
      "x0": 0.5338709677419355,
      "x1": 0.6338709677419355
    },
    {
      "name": "COL5",
      "x0": 0.6338709677419355,
      "x1": 0.7685483870967742
    },
    {
      "name": "AMOUNT",
      "x0": 0.7685483870967742,
      "x1": 0.9036290322580645
    },
    {
      "name": "COL7",
      "x0": 0.9036290322580645,
      "x1": 1.0
    }
  ]
}